{
  "1": {
    "type": "mult",
    "en": {
      "text": "Group",
      "variants": [
        "Igor, Irina, Konstantin",
        "Sasha, Idar, Artem",
        "Anton, Azamat, Alexandr",
        "Pavel, Alexandra",
        "Artur, Vyacheslav, Bulat"
      ]
    },
    "ru": {
      "text": "Группа",
      "variants": [
        "Igor, Irina, Konstantin",
        "Sasha, Idar, Artem",
        "Anton, Azamat, Alexandr",
        "Pavel, Alexandra",
        "Artur, Vyacheslav, Bulat"
      ]
    }
  },
  "2": {
    "type": "num",
    "en": {
      "text": "Deployment process:  is it good and is it clearly described?",
      "variants": [
        "1",
        "10",
        "1"
      ]
    },
    "ru": {
      "text": "Описание интеграции",
      "variants": [
        "1",
        "10",
        "1"
      ]
    }
  },
  "3": {
    "type": "num",
    "en": {
      "text": "Does the application meet all the requirements?",
      "variants": [
        "1",
        "20",
        "1"
      ]
    },
    "ru": {
      "text": "Качество приложения",
      "variants": [
        "1",
        "20",
        "1"
      ]
    }
  },
  "4": {
    "type": "num",
    "en": {
      "text": "Are the scaling option well chosen and well described?  Is this a good way to scale?",
      "variants": [
        "1",
        "20",
        "1"
      ]
    },
    "ru": {
      "text": "Описание маштабируемости",
      "variants": [
        "1",
        "20",
        "1"
      ]
    }
  },
  "5": {
    "type": "num",
    "en": {
      "text": "Are the management options well described?  Do they describe the management information you would want for your application?",
      "variants": [
        "1",
        "20",
        "1"
      ]
    },
    "ru": {
      "text": "Описание опций управления",
      "variants": [
        "1",
        "20",
        "1"
      ]
    }
  },
  "6": {
    "type": "num",
    "en": {
      "text": "Are the analytics well described? Do they describe how you would get the information you would want and why this is a good approach?",
      "variants": [
        "1",
        "20",
        "1"
      ]
    },
    "ru": {
      "text": "Описание возможностей мониторинга",
      "variants": [
        "1",
        "20",
        "1"
      ]
    },
    "7": {
      "type": "num",
      "en": {
        "text": "Is the comparison between IaaS and PaaS clear and convincing?",
        "variants": [
          "1",
          "10",
          "1"
        ]
      },
      "ru": {
        "text": "Сравнение PaaS и IaaS",
        "variants": [
          "1",
          "10",
          "1"
        ]
      }
    }
  }
}